{
	"name": "Trigger 1",
	"properties": {
		"annotations": [],
		"runtimeState": "Started",
		"pipelines": [
			{
				"pipelineReference": {
					"referenceName": "Pipeline_Customers",
					"type": "PipelineReference"
				}
			}
		],
		"type": "ScheduleTrigger",
		"typeProperties": {
			"recurrence": {
				"frequency": "Week",
				"interval": 1,
				"startTime": "2024-05-06T14:10:00",
				"timeZone": "Central European Standard Time",
				"schedule": {
					"weekDays": [
						"Monday"
					]
				}
			}
		}
	}
}